LICENSE.txt
MANIFEST.in
README.md
setup.cfg
setup.py
django_schedulermanager/__init__.py
django_schedulermanager/apps.py
django_schedulermanager/decorators.py
django_schedulermanager/manager.py
django_schedulermanager.egg-info/PKG-INFO
django_schedulermanager.egg-info/SOURCES.txt
django_schedulermanager.egg-info/dependency_links.txt
django_schedulermanager.egg-info/requires.txt
django_schedulermanager.egg-info/top_level.txt
django_schedulermanager/management/__init__.py
django_schedulermanager/management/commands/__init__.py
django_schedulermanager/management/commands/schedulejob.py
django_schedulermanager/management/commands/unschedulejob.py
django_schedulermanager/migrations/__init__.py