Metadata-Version: 1.1
Name: django-schedulermanager
Version: 1.0.1
Summary: A package that allows you to schedule and unschedule jobs
Home-page: https://github.com/marcoacierno/django-schedulermanager/
Author: Marco Acierno
Author-email: marcoaciernoemail@gmail.com
License: MIT
Keywords: django_schedulermanager
Platform: UNKNOWN
Classifier: Development Status :: 4 - Beta
Classifier: Intended Audience :: Developers
Classifier: License :: OSI Approved :: MIT License
Classifier: Topic :: Software Development :: Libraries :: Python Modules
Classifier: Operating System :: OS Independent
Classifier: Programming Language :: Python :: 2.7
Classifier: Programming Language :: Python :: 3
Classifier: Programming Language :: Python :: 3.2
Classifier: Programming Language :: Python :: 3.3
Classifier: Programming Language :: Python :: 3.4
Classifier: Programming Language :: Python :: 3.5
Classifier: Framework :: Django :: 1.10
Classifier: Framework :: Django :: 1.9
Classifier: Framework :: Django :: 1.8
Classifier: Framework :: Django
